memstate/__init__.py
memstate/constants.py
memstate/exceptions.py
memstate/schemas.py
memstate/storage.py
memstate/types.py
memstate/backends/__init__.py
memstate/backends/base.py
memstate/backends/inmemory.py
memstate/backends/postgres.py
memstate/backends/redis.py
memstate/backends/sqlite.py
memstate/integrations/__init__.py
memstate/integrations/chroma.py
memstate/integrations/langgraph.py
memstate/integrations/qdrant.py
memstate-0.5.1.dist-info/METADATA
memstate-0.5.1.dist-info/WHEEL
memstate-0.5.1.dist-info/licenses/LICENSE
memstate-0.5.1.dist-info/RECORD
