Metadata-Version: 2.4
Name: memstate
Version: 0.5.1
Summary: Transactional Memory for AI Agents - Keep SQL and Vector DBs in sync with ACID-like guarantees
Project-URL: Homepage, https://github.com/scream4ik/MemState
Project-URL: Repository, https://github.com/scream4ik/MemState
Project-URL: Issues, https://github.com/scream4ik/MemState/issues
Author: Slava Kurachevsky
License: Apache-2.0
License-File: LICENSE
Keywords: acid,agents,ai,atomicity,consistency,langchain,langgraph,llm,memory,pydantic,sqlite,state-management
Classifier: Development Status :: 4 - Beta
Classifier: Intended Audience :: Developers
Classifier: License :: OSI Approved :: Apache Software License
Classifier: Programming Language :: Python :: 3
Classifier: Programming Language :: Python :: 3.10
Classifier: Programming Language :: Python :: 3.11
Classifier: Programming Language :: Python :: 3.12
Classifier: Programming Language :: Python :: 3.13
Classifier: Programming Language :: Python :: 3.14
Classifier: Topic :: Database
Classifier: Topic :: Scientific/Engineering :: Artificial Intelligence
Classifier: Topic :: Software Development :: Libraries :: Python Modules
Requires-Python: >=3.10
Requires-Dist: pydantic>=2.12.4
Provides-Extra: chromadb
Requires-Dist: chromadb>=1.3.5; extra == 'chromadb'
Provides-Extra: langgraph
Requires-Dist: langgraph>=1.0.4; extra == 'langgraph'
Provides-Extra: postgres
Requires-Dist: psycopg[binary]>=3.3.2; extra == 'postgres'
Requires-Dist: sqlalchemy>=2.0.0; extra == 'postgres'
Provides-Extra: qdrant
Requires-Dist: qdrant-client>=1.16.2; extra == 'qdrant'
Provides-Extra: redis
Requires-Dist: redis>=7.1.0; extra == 'redis'
Provides-Extra: sqlite-async
Requires-Dist: aiosqlite>=0.22.0; extra == 'sqlite-async'
